{
  "question": "How much can we speed up Boltz-2 GPU inference while keeping per-complex lDDT within 2 percentage points of the baseline?",
  "references": [
    "https://github.com/jwohlwend/boltz",
    "https://doi.org/10.1101/2024.11.19.624167",
    "https://doi.org/10.1101/2025.06.14.659707",
    "https://doi.org/10.1038/s41586-024-07487-w"
  ],
  "project_name": "boltz",
  "status": "ready",
  "setup_phase": 4,
  "eval_version": "eval-v1",
  "direction": "maximize",
  "metric_name": "speedup_at_iso_quality",
  "best_metric": null,
  "best_orbit": null,
  "campaign_url": "https://github.com/canele-ai/boltz/issues/2",
  "campaign_issue": 2
}
